{
    "todoitems": [
        {
            "name": "topical paper 2",
            "due_date": "Tuesday November 09 2021",
            "number": 1,
            "is_done_check": "[X]",
            "class_name": "ethics"
        },
        {
            "name": "assignment 8",
            "due_date": "Monday November 08 2021",
            "number": 2,
            "is_done_check": "[X]",
            "class_name": "web"
        },
        {
            "name": "homework 8",
            "due_date": "Tuesday November 09 2021",
            "number": 3,
            "is_done_check": "[X]",
            "class_name": "struct"
        },
        {
            "name": "quiz 7",
            "due_date": "Tuesday November 09 2021",
            "number": 4,
            "is_done_check": "[X]",
            "class_name": "struct"
        },
        {
            "name": "homework 9 on paper",
            "due_date": "Thursday November 11 2021",
            "number": 5,
            "is_done_check": "[ ]",
            "class_name": "struct"
        },
        {
            "name": "quiz 8",
            "due_date": "Thursday November 11 2021",
            "number": 6,
            "is_done_check": "[ ]",
            "class_name": "struct"
        },
        {
            "name": "flipgrid 7",
            "due_date": "Thursday November 11 2021",
            "number": 7,
            "is_done_check": "[ ]",
            "class_name": "rhet"
        }
    ]
}